main.py
credit_mcp-0.1.0.dist-info/METADATA
credit_mcp-0.1.0.dist-info/WHEEL
credit_mcp-0.1.0.dist-info/top_level.txt
credit_mcp-0.1.0.dist-info/RECORD
