Metadata-Version: 2.4
Name: credit-mcp
Version: 0.1.0
Summary: Add your description here
Requires-Python: >=3.11
Requires-Dist: mcp[cli]>=1.19.0
